setup.cfg
setup.py
mercedes_api.egg-info/PKG-INFO
mercedes_api.egg-info/SOURCES.txt
mercedes_api.egg-info/dependency_links.txt
mercedes_api.egg-info/requires.txt
mercedes_api.egg-info/top_level.txt
mercedesapi/__init__.py
test/test_get_request.py
test/test_post_request.py