Metadata-Version: 1.1
Name: mercedes-api
Version: 0.0.3
Summary: Retrieve info from mercedes api.
Home-page: https://github.com/RiRomain/python-mercedes-api/
Author: RiTomain
Author-email: romain.rinie@googlemail.com
License: MIT
Platform: UNKNOWN
Classifier: License :: OSI Approved :: MIT License
Classifier: Operating System :: OS Independent
Classifier: Programming Language :: Python :: 3
Classifier: Development Status :: 4 - Beta
Classifier: Intended Audience :: Developers
